agent_eval/__init__.py
agent_eval/__main__.py
agent_eval/cli.py
agent_eval/analysis/__init__.py
agent_eval/analysis/cognitive_analyzer.py
agent_eval/analysis/confidence_analyzer.py
agent_eval/analysis/fix_generator.py
agent_eval/analysis/interactive_analyst.py
agent_eval/analysis/judge_comparison.py
agent_eval/analysis/pattern_learner.py
agent_eval/analysis/remediation_engine.py
agent_eval/analysis/self_improvement.py
agent_eval/analysis/universal_failure_classifier.py
agent_eval/benchmarks/__init__.py
agent_eval/benchmarks/adapter.py
agent_eval/benchmarks/providers/__init__.py
agent_eval/benchmarks/providers/gsm8k.py
agent_eval/benchmarks/providers/humeval.py
agent_eval/benchmarks/providers/mmlu.py
agent_eval/commands/__init__.py
agent_eval/commands/analyze_command.py
agent_eval/commands/base.py
agent_eval/commands/benchmark_command.py
agent_eval/commands/compliance_command.py
agent_eval/commands/compliance_handler.py
agent_eval/commands/debug_command.py
agent_eval/commands/improve_command.py
agent_eval/commands/reliability_command.py
agent_eval/commands/reliability_handler.py
agent_eval/commands/workflow_handler.py
agent_eval/core/__init__.py
agent_eval/core/comparison_engine.py
agent_eval/core/config.py
agent_eval/core/constants.py
agent_eval/core/engine.py
agent_eval/core/framework_intelligence.py
agent_eval/core/framework_patterns.py
agent_eval/core/improvement_planner.py
agent_eval/core/input_detector.py
agent_eval/core/input_helpers.py
agent_eval/core/parser_registry.py
agent_eval/core/scenario_bank.py
agent_eval/core/types.py
agent_eval/core/workflow_state.py
agent_eval/domains/__init__.py
agent_eval/domains/finance.yaml
agent_eval/domains/ml.yaml
agent_eval/domains/reliability.yaml
agent_eval/domains/security.yaml
agent_eval/evaluation/__init__.py
agent_eval/evaluation/bias_detection.py
agent_eval/evaluation/confidence_calibrator.py
agent_eval/evaluation/objective_analyzer.py
agent_eval/evaluation/performance_tracker.py
arc_eval-0.2.9.dist-info/licenses/LICENSE
arc_eval-0.2.9.dist-info/METADATA
arc_eval-0.2.9.dist-info/WHEEL
arc_eval-0.2.9.dist-info/entry_points.txt
arc_eval-0.2.9.dist-info/top_level.txt
arc_eval-0.2.9.dist-info/RECORD
