Metadata-Version: 2.4
Name: arc-eval
Version: 0.2.9
Summary: ARC-Eval: Agent Reliability & Compliance evaluation platform for LLMs and AI agents
Author: AgentEval Team
License-Expression: MIT
Project-URL: Homepage, https://github.com/arc-computer/arc-eval
Project-URL: Repository, https://github.com/arc-computer/arc-eval
Project-URL: Documentation, https://github.com/arc-computer/arc-eval/blob/main/README.md
Keywords: ai,llm,agent,evaluation,compliance,security,finance,ml,audit
Classifier: Development Status :: 3 - Alpha
Classifier: Intended Audience :: Developers
Classifier: Operating System :: OS Independent
Classifier: Programming Language :: Python :: 3
Classifier: Programming Language :: Python :: 3.9
Classifier: Programming Language :: Python :: 3.10
Classifier: Programming Language :: Python :: 3.11
Classifier: Programming Language :: Python :: 3.12
Requires-Python: >=3.9
License-File: LICENSE
Requires-Dist: click>=8.0.0
Requires-Dist: pyyaml>=6.0
Requires-Dist: rich>=13.0.0
Requires-Dist: reportlab>=4.0.0
Requires-Dist: tabulate>=0.9.0
Requires-Dist: psutil>=5.9.0
Requires-Dist: anthropic>=0.18.0
Requires-Dist: openai>=1.0.0
Requires-Dist: google-genai>=1.18.0
Provides-Extra: dev
Requires-Dist: pytest>=7.0.0; extra == "dev"
Requires-Dist: pytest-cov>=4.0.0; extra == "dev"
Requires-Dist: black>=23.0.0; extra == "dev"
Requires-Dist: flake8>=6.0.0; extra == "dev"
Requires-Dist: mypy>=1.0.0; extra == "dev"
Dynamic: license-file
Dynamic: requires-python
